magnum/__init__.py
magnum/aclddevice.py
magnum/agsdevice.py
magnum/bmkdevice.py
magnum/inverterdevice.py
magnum/mag2sql.py
magnum/magdump.py
magnum/magnum.py
magnum/magparser.py
magnum/magtest.py
magnum/pt100device.py
magnum/remotedevice.py
magnum/rtrdevice.py
magnum/write_packets.py
pymagnum-2.0.5.dist-info/LICENSE
pymagnum-2.0.5.dist-info/METADATA
pymagnum-2.0.5.dist-info/WHEEL
pymagnum-2.0.5.dist-info/entry_points.txt
pymagnum-2.0.5.dist-info/top_level.txt
pymagnum-2.0.5.dist-info/RECORD
