Metadata-Version: 2.1
Name: pymagnum
Version: 2.0.5
Summary: Magnum Energy Network Interface (read-only)
Home-page: https://github.com/CharlesGodwin/pymagnum
Author: Charles Godwin
Author-email: magnum@godwin.ca
License: BSD
Keywords: Magnum Energy Renewable Solar Network RS485 IoT
Classifier: Programming Language :: Python :: 3 :: Only
Classifier: License :: OSI Approved :: BSD License
Classifier: Operating System :: OS Independent
Requires-Python: >=3.7
License-File: LICENSE
Requires-Dist: pyserial
Requires-Dist: uptime
